[
  {
    "file_name": "Gate.Gate002.json",
    "is_locked": false,
    "editor_layer": 0,
    "editor_layer_name": "Layer1Walls",
    "editor_layer_visibility": true
  },
  {
    "file_name": "Wall.Wall004.json",
    "is_locked": false,
    "editor_layer": 0,
    "editor_layer_name": "Layer1Walls",
    "editor_layer_visibility": true
  },
  {
    "file_name": "Wall.sw01.json",
    "is_locked": true,
    "editor_layer": 4,
    "editor_layer_name": "DropTargets",
    "editor_layer_visibility": true
  },
  {
    "file_name": "Wall.Wall39.json",
    "is_locked": false,
    "editor_layer": 1,
    "editor_layer_name": "Subway",
    "editor_layer_visibility": true
  },
  {
    "file_name": "Wall.Wall39Floor.json",
    "is_locked": false,
    "editor_layer": 0,
    "editor_layer_name": "Subway",
    "editor_layer_visibility": true
  },
  {
    "file_name": "Primitive.Primitive002.json",
    "is_locked": true,
    "editor_layer": 0,
    "editor_layer_name": "Layer1Ramps",
    "editor_layer_visibility": true
  },
  {
    "file_name": "Wall.UpperPf.json",
    "is_locked": false,
    "editor_layer": 1,
    "editor_layer_name": "UpperPF",
    "editor_layer_visibility": true
  },
  {
    "file_name": "Wall.Wall015.json",
    "is_locked": false,
    "editor_layer": 0,
    "editor_layer_name": "Main Layer",
    "editor_layer_visibility": true
  },
  {
    "file_name": "Ramp.Ramp002.json",
    "is_locked": true,
    "editor_layer": 0,
    "editor_layer_name": "Layer1Ramps",
    "editor_layer_visibility": true
  },
  {
    "file_name": "Trigger.sw1.json",
    "is_locked": true,
    "editor_layer": 0,
    "editor_layer_name": "switchs",
    "editor_layer_visibility": true
  },
  {
    "file_name": "Trigger.swPlunger.json",
    "is_locked": true,
    "editor_layer": 0,
    "editor_layer_name": "Main Layer",
    "editor_layer_visibility": true
  },
  {
    "file_name": "Gate.Gate001.json",
    "is_locked": true,
    "editor_layer": 0,
    "editor_layer_name": "Main Layer",
    "editor_layer_visibility": true
  },
  {
    "file_name": "Wall.Wall78.json",
    "is_locked": true,
    "editor_layer": 0,
    "editor_layer_name": "Layer1Walls",
    "editor_layer_visibility": true
  },
  {
    "file_name": "Wall.Wall5top.json",
    "is_locked": true,
    "editor_layer": 0,
    "editor_layer_name": "Layer1Walls",
    "editor_layer_visibility": true
  },
  {
    "file_name": "Wall.Wall350.json",
    "is_locked": true,
    "editor_layer": 0,
    "editor_layer_name": "Layer1Walls",
    "editor_layer_visibility": true
  },
  {
    "file_name": "Wall.Wall3.json",
    "is_locked": true,
    "editor_layer": 0,
    "editor_layer_name": "Layer1Walls",
    "editor_layer_visibility": true
  },
  {
    "file_name": "Wall.Wall4.json",
    "is_locked": true,
    "editor_layer": 0,
    "editor_layer_name": "Layer1Walls",
    "editor_layer_visibility": true
  },
  {
    "file_name": "Timer.GameTimer.json",
    "is_locked": true,
    "editor_layer": 0,
    "editor_layer_name": "Main Layer",
    "editor_layer_visibility": true
  },
  {
    "file_name": "Trigger.BIPL.json",
    "is_locked": true,
    "editor_layer": 0,
    "editor_layer_name": "Main Layer",
    "editor_layer_visibility": true
  },
  {
    "file_name": "Kicker.swTrough1.json",
    "is_locked": true,
    "editor_layer": 0,
    "editor_layer_name": "Main Layer",
    "editor_layer_visibility": true
  },
  {
    "file_name": "Wall.Wall15.json",
    "is_locked": true,
    "editor_layer": 0,
    "editor_layer_name": "Main Layer",
    "editor_layer_visibility": true
  },
  {
    "file_name": "Primitive.FlipperLSh.json",
    "is_locked": true,
    "editor_layer": 4,
    "editor_layer_name": "Shadows",
    "editor_layer_visibility": true
  },
  {
    "file_name": "Primitive.FlipperRSh.json",
    "is_locked": true,
    "editor_layer": 4,
    "editor_layer_name": "Shadows",
    "editor_layer_visibility": true
  },
  {
    "file_name": "Timer.FrameTimer.json",
    "is_locked": true,
    "editor_layer": 0,
    "editor_layer_name": "Main Layer",
    "editor_layer_visibility": true
  },
  {
    "file_name": "Flipper.LeftFlipper.json",
    "is_locked": false,
    "editor_layer": 0,
    "editor_layer_name": "Main Layer",
    "editor_layer_visibility": true
  },
  {
    "file_name": "Flipper.RightFlipper.json",
    "is_locked": false,
    "editor_layer": 0,
    "editor_layer_name": "Main Layer",
    "editor_layer_visibility": true
  },
  {
    "file_name": "Primitive.BallShadow0.json",
    "is_locked": true,
    "editor_layer": 4,
    "editor_layer_name": "Shadows",
    "editor_layer_visibility": true
  },
  {
    "file_name": "Kicker.Drain.json",
    "is_locked": true,
    "editor_layer": 0,
    "editor_layer_name": "Main Layer",
    "editor_layer_visibility": true
  },
  {
    "file_name": "Primitive.EndPointLp.json",
    "is_locked": false,
    "editor_layer": 0,
    "editor_layer_name": "Main Layer",
    "editor_layer_visibility": true
  },
  {
    "file_name": "Trigger.TriggerLF.json",
    "is_locked": false,
    "editor_layer": 0,
    "editor_layer_name": "Main Layer",
    "editor_layer_visibility": true
  },
  {
    "file_name": "Trigger.TriggerRF.json",
    "is_locked": false,
    "editor_layer": 0,
    "editor_layer_name": "Main Layer",
    "editor_layer_visibility": true
  },
  {
    "file_name": "Primitive.EndPointRp.json",
    "is_locked": false,
    "editor_layer": 0,
    "editor_layer_name": "Main Layer",
    "editor_layer_visibility": true
  },
  {
    "file_name": "Plunger.Plunger.json",
    "is_locked": true,
    "editor_layer": 0,
    "editor_layer_name": "Main Layer",
    "editor_layer_visibility": true
  },
  {
    "file_name": "TextBox.tbWR.json",
    "is_locked": false,
    "editor_layer": 0,
    "editor_layer_name": "Main Layer",
    "editor_layer_visibility": true
  },
  {
    "file_name": "Timer.RampRoll.json",
    "is_locked": true,
    "editor_layer": 0,
    "editor_layer_name": "Main Layer",
    "editor_layer_visibility": true
  },
  {
    "file_name": "Timer.LampTimer.json",
    "is_locked": true,
    "editor_layer": 0,
    "editor_layer_name": "Main Layer",
    "editor_layer_visibility": true
  },
  {
    "file_name": "Timer.BallSaverTimerExpired.json",
    "is_locked": true,
    "editor_layer": 0,
    "editor_layer_name": "Main Layer",
    "editor_layer_visibility": true
  },
  {
    "file_name": "Timer.BumperTimer.json",
    "is_locked": true,
    "editor_layer": 0,
    "editor_layer_name": "Main Layer",
    "editor_layer_visibility": true
  },
  {
    "file_name": "Timer.DMDTimer.json",
    "is_locked": true,
    "editor_layer": 0,
    "editor_layer_name": "Main Layer",
    "editor_layer_visibility": true
  },
  {
    "file_name": "Timer.cardtimer.json",
    "is_locked": true,
    "editor_layer": 0,
    "editor_layer_name": "Main Layer",
    "editor_layer_visibility": true
  },
  {
    "file_name": "Timer.GITimer.json",
    "is_locked": true,
    "editor_layer": 0,
    "editor_layer_name": "Main Layer",
    "editor_layer_visibility": true
  },
  {
    "file_name": "Wall.Wall001.json",
    "is_locked": true,
    "editor_layer": 0,
    "editor_layer_name": "Layer1Walls",
    "editor_layer_visibility": true
  },
  {
    "file_name": "Kicker.swTrough2.json",
    "is_locked": true,
    "editor_layer": 0,
    "editor_layer_name": "Main Layer",
    "editor_layer_visibility": true
  },
  {
    "file_name": "Kicker.swTrough3.json",
    "is_locked": true,
    "editor_layer": 0,
    "editor_layer_name": "Main Layer",
    "editor_layer_visibility": true
  },
  {
    "file_name": "Kicker.swTrough4.json",
    "is_locked": true,
    "editor_layer": 0,
    "editor_layer_name": "Main Layer",
    "editor_layer_visibility": true
  },
  {
    "file_name": "Kicker.swTrough5.json",
    "is_locked": true,
    "editor_layer": 0,
    "editor_layer_name": "Main Layer",
    "editor_layer_visibility": true
  },
  {
    "file_name": "Timer.UpdateTroughTimer.json",
    "is_locked": true,
    "editor_layer": 0,
    "editor_layer_name": "Main Layer",
    "editor_layer_visibility": true
  },
  {
    "file_name": "Timer.PulseTimer.json",
    "is_locked": true,
    "editor_layer": 0,
    "editor_layer_name": "Main Layer",
    "editor_layer_visibility": true
  },
  {
    "file_name": "Flasher.BallShadowA0.json",
    "is_locked": true,
    "editor_layer": 4,
    "editor_layer_name": "Shadows",
    "editor_layer_visibility": true
  },
  {
    "file_name": "Primitive.BallShadow1.json",
    "is_locked": true,
    "editor_layer": 4,
    "editor_layer_name": "Shadows",
    "editor_layer_visibility": true
  },
  {
    "file_name": "Primitive.BallShadow2.json",
    "is_locked": true,
    "editor_layer": 4,
    "editor_layer_name": "Shadows",
    "editor_layer_visibility": true
  },
  {
    "file_name": "Primitive.BallShadow3.json",
    "is_locked": true,
    "editor_layer": 4,
    "editor_layer_name": "Shadows",
    "editor_layer_visibility": true
  },
  {
    "file_name": "Primitive.BallShadow4.json",
    "is_locked": true,
    "editor_layer": 4,
    "editor_layer_name": "Shadows",
    "editor_layer_visibility": true
  },
  {
    "file_name": "Flasher.BallShadowA1.json",
    "is_locked": true,
    "editor_layer": 4,
    "editor_layer_name": "Shadows",
    "editor_layer_visibility": true
  },
  {
    "file_name": "Flasher.BallShadowA2.json",
    "is_locked": true,
    "editor_layer": 4,
    "editor_layer_name": "Shadows",
    "editor_layer_visibility": true
  },
  {
    "file_name": "Flasher.BallShadowA3.json",
    "is_locked": true,
    "editor_layer": 4,
    "editor_layer_name": "Shadows",
    "editor_layer_visibility": true
  },
  {
    "file_name": "Flasher.BallShadowA4.json",
    "is_locked": true,
    "editor_layer": 4,
    "editor_layer_name": "Shadows",
    "editor_layer_visibility": true
  },
  {
    "file_name": "Primitive.RtxBallShadow0.json",
    "is_locked": true,
    "editor_layer": 4,
    "editor_layer_name": "Shadows",
    "editor_layer_visibility": true
  },
  {
    "file_name": "Primitive.RtxBall2Shadow0.json",
    "is_locked": true,
    "editor_layer": 4,
    "editor_layer_name": "Shadows",
    "editor_layer_visibility": true
  },
  {
    "file_name": "Primitive.RtxBall2Shadow1.json",
    "is_locked": true,
    "editor_layer": 4,
    "editor_layer_name": "Shadows",
    "editor_layer_visibility": true
  },
  {
    "file_name": "Primitive.RtxBall2Shadow2.json",
    "is_locked": true,
    "editor_layer": 4,
    "editor_layer_name": "Shadows",
    "editor_layer_visibility": true
  },
  {
    "file_name": "Primitive.RtxBall2Shadow3.json",
    "is_locked": true,
    "editor_layer": 4,
    "editor_layer_name": "Shadows",
    "editor_layer_visibility": true
  },
  {
    "file_name": "Primitive.RtxBall2Shadow4.json",
    "is_locked": true,
    "editor_layer": 4,
    "editor_layer_name": "Shadows",
    "editor_layer_visibility": true
  },
  {
    "file_name": "Primitive.RtxBallShadow1.json",
    "is_locked": true,
    "editor_layer": 4,
    "editor_layer_name": "Shadows",
    "editor_layer_visibility": true
  },
  {
    "file_name": "Primitive.RtxBallShadow2.json",
    "is_locked": true,
    "editor_layer": 4,
    "editor_layer_name": "Shadows",
    "editor_layer_visibility": true
  },
  {
    "file_name": "Primitive.RtxBallShadow3.json",
    "is_locked": true,
    "editor_layer": 4,
    "editor_layer_name": "Shadows",
    "editor_layer_visibility": true
  },
  {
    "file_name": "Primitive.RtxBallShadow4.json",
    "is_locked": true,
    "editor_layer": 4,
    "editor_layer_name": "Shadows",
    "editor_layer_visibility": true
  },
  {
    "file_name": "TextBox.Listener001.json",
    "is_locked": false,
    "editor_layer": 0,
    "editor_layer_name": "Main Layer",
    "editor_layer_visibility": true
  },
  {
    "file_name": "TextBox.Listener002.json",
    "is_locked": false,
    "editor_layer": 0,
    "editor_layer_name": "Main Layer",
    "editor_layer_visibility": true
  },
  {
    "file_name": "TextBox.Listener003.json",
    "is_locked": false,
    "editor_layer": 0,
    "editor_layer_name": "Main Layer",
    "editor_layer_visibility": true
  },
  {
    "file_name": "TextBox.Listener004.json",
    "is_locked": false,
    "editor_layer": 0,
    "editor_layer_name": "Main Layer",
    "editor_layer_visibility": true
  },
  {
    "file_name": "TextBox.Listener005.json",
    "is_locked": false,
    "editor_layer": 0,
    "editor_layer_name": "Main Layer",
    "editor_layer_visibility": true
  },
  {
    "file_name": "TextBox.Listener006.json",
    "is_locked": false,
    "editor_layer": 0,
    "editor_layer_name": "Main Layer",
    "editor_layer_visibility": true
  },
  {
    "file_name": "TextBox.Listener007.json",
    "is_locked": false,
    "editor_layer": 0,
    "editor_layer_name": "Main Layer",
    "editor_layer_visibility": true
  },
  {
    "file_name": "TextBox.Listener008.json",
    "is_locked": false,
    "editor_layer": 0,
    "editor_layer_name": "Main Layer",
    "editor_layer_visibility": true
  },
  {
    "file_name": "TextBox.Listener009.json",
    "is_locked": false,
    "editor_layer": 0,
    "editor_layer_name": "Main Layer",
    "editor_layer_visibility": true
  },
  {
    "file_name": "TextBox.Listener010.json",
    "is_locked": false,
    "editor_layer": 0,
    "editor_layer_name": "Main Layer",
    "editor_layer_visibility": true
  },
  {
    "file_name": "Timer.vpmTimer.json",
    "is_locked": true,
    "editor_layer": 0,
    "editor_layer_name": "Main Layer",
    "editor_layer_visibility": true
  },
  {
    "file_name": "Primitive.BallShadow5.json",
    "is_locked": true,
    "editor_layer": 4,
    "editor_layer_name": "Shadows",
    "editor_layer_visibility": true
  },
  {
    "file_name": "Primitive.RtxBallShadow5.json",
    "is_locked": true,
    "editor_layer": 4,
    "editor_layer_name": "Shadows",
    "editor_layer_visibility": true
  },
  {
    "file_name": "Primitive.RtxBall2Shadow5.json",
    "is_locked": true,
    "editor_layer": 4,
    "editor_layer_name": "Shadows",
    "editor_layer_visibility": true
  },
  {
    "file_name": "Flasher.BallShadowA5.json",
    "is_locked": true,
    "editor_layer": 4,
    "editor_layer_name": "Shadows",
    "editor_layer_visibility": true
  },
  {
    "file_name": "Timer.SpinnerBallTimer.json",
    "is_locked": true,
    "editor_layer": 10,
    "editor_layer_name": "Main Layer",
    "editor_layer_visibility": true
  },
  {
    "file_name": "Primitive.BallShadow6.json",
    "is_locked": true,
    "editor_layer": 4,
    "editor_layer_name": "More Shadows?",
    "editor_layer_visibility": true
  },
  {
    "file_name": "Primitive.BallShadow7.json",
    "is_locked": true,
    "editor_layer": 4,
    "editor_layer_name": "More Shadows?",
    "editor_layer_visibility": true
  },
  {
    "file_name": "Primitive.RtxBallShadow6.json",
    "is_locked": true,
    "editor_layer": 4,
    "editor_layer_name": "More Shadows?",
    "editor_layer_visibility": true
  },
  {
    "file_name": "Primitive.RtxBallShadow7.json",
    "is_locked": true,
    "editor_layer": 4,
    "editor_layer_name": "More Shadows?",
    "editor_layer_visibility": true
  },
  {
    "file_name": "Primitive.RtxBall2Shadow6.json",
    "is_locked": true,
    "editor_layer": 4,
    "editor_layer_name": "More Shadows?",
    "editor_layer_visibility": true
  },
  {
    "file_name": "Primitive.RtxBall2Shadow7.json",
    "is_locked": true,
    "editor_layer": 4,
    "editor_layer_name": "More Shadows?",
    "editor_layer_visibility": true
  },
  {
    "file_name": "Flasher.BallShadowA6.json",
    "is_locked": true,
    "editor_layer": 4,
    "editor_layer_name": "More Shadows?",
    "editor_layer_visibility": true
  },
  {
    "file_name": "Flasher.BallShadowA7.json",
    "is_locked": true,
    "editor_layer": 4,
    "editor_layer_name": "More Shadows?",
    "editor_layer_visibility": true
  },
  {
    "file_name": "Timer.BallReleaseTimer.json",
    "is_locked": true,
    "editor_layer": 0,
    "editor_layer_name": "Main Layer",
    "editor_layer_visibility": true
  },
  {
    "file_name": "Timer.AutoPlungerDelay.json",
    "is_locked": true,
    "editor_layer": 0,
    "editor_layer_name": "Main Layer",
    "editor_layer_visibility": true
  },
  {
    "file_name": "Ramp.Ramp001.json",
    "is_locked": false,
    "editor_layer": 0,
    "editor_layer_name": "Main Layer",
    "editor_layer_visibility": true
  },
  {
    "file_name": "Wall.Wall006.json",
    "is_locked": true,
    "editor_layer": 0,
    "editor_layer_name": "Main Layer",
    "editor_layer_visibility": true
  },
  {
    "file_name": "Trigger.BIPL_Top.json",
    "is_locked": true,
    "editor_layer": 0,
    "editor_layer_name": "Main Layer",
    "editor_layer_visibility": true
  },
  {
    "file_name": "Wall.Wall011.json",
    "is_locked": true,
    "editor_layer": 0,
    "editor_layer_name": "Layer1Ramps",
    "editor_layer_visibility": true
  },
  {
    "file_name": "Light.l33.json",
    "is_locked": false,
    "editor_layer": 8,
    "editor_layer_name": "LampsPF",
    "editor_layer_visibility": true
  },
  {
    "file_name": "Light.l31.json",
    "is_locked": false,
    "editor_layer": 8,
    "editor_layer_name": "LampsPF",
    "editor_layer_visibility": true
  },
  {
    "file_name": "Light.l30.json",
    "is_locked": false,
    "editor_layer": 8,
    "editor_layer_name": "LampsPF",
    "editor_layer_visibility": true
  },
  {
    "file_name": "Light.l28.json",
    "is_locked": false,
    "editor_layer": 8,
    "editor_layer_name": "LampsPF",
    "editor_layer_visibility": true
  },
  {
    "file_name": "Light.l29.json",
    "is_locked": false,
    "editor_layer": 8,
    "editor_layer_name": "LampsPF",
    "editor_layer_visibility": true
  },
  {
    "file_name": "Light.l32.json",
    "is_locked": false,
    "editor_layer": 8,
    "editor_layer_name": "LampsPF",
    "editor_layer_visibility": true
  },
  {
    "file_name": "Light.l34.json",
    "is_locked": false,
    "editor_layer": 8,
    "editor_layer_name": "LampsPF",
    "editor_layer_visibility": true
  },
  {
    "file_name": "Light.l35.json",
    "is_locked": false,
    "editor_layer": 8,
    "editor_layer_name": "LampsPF",
    "editor_layer_visibility": true
  },
  {
    "file_name": "Light.l15.json",
    "is_locked": false,
    "editor_layer": 8,
    "editor_layer_name": "LampsPF",
    "editor_layer_visibility": true
  },
  {
    "file_name": "Light.l11.json",
    "is_locked": false,
    "editor_layer": 8,
    "editor_layer_name": "LampsPF",
    "editor_layer_visibility": true
  },
  {
    "file_name": "Light.l45.json",
    "is_locked": false,
    "editor_layer": 8,
    "editor_layer_name": "LampsPF",
    "editor_layer_visibility": true
  },
  {
    "file_name": "Light.l44.json",
    "is_locked": false,
    "editor_layer": 8,
    "editor_layer_name": "LampsPF",
    "editor_layer_visibility": true
  },
  {
    "file_name": "Light.l43.json",
    "is_locked": false,
    "editor_layer": 8,
    "editor_layer_name": "LampsPF",
    "editor_layer_visibility": true
  },
  {
    "file_name": "Light.l42.json",
    "is_locked": false,
    "editor_layer": 8,
    "editor_layer_name": "LampsPF",
    "editor_layer_visibility": true
  },
  {
    "file_name": "Light.l65.json",
    "is_locked": false,
    "editor_layer": 8,
    "editor_layer_name": "LampsPF",
    "editor_layer_visibility": true
  },
  {
    "file_name": "Light.l66.json",
    "is_locked": false,
    "editor_layer": 8,
    "editor_layer_name": "LampsPF",
    "editor_layer_visibility": true
  },
  {
    "file_name": "Light.l67.json",
    "is_locked": false,
    "editor_layer": 8,
    "editor_layer_name": "LampsPF",
    "editor_layer_visibility": true
  },
  {
    "file_name": "Light.l68.json",
    "is_locked": false,
    "editor_layer": 8,
    "editor_layer_name": "LampsPF",
    "editor_layer_visibility": true
  },
  {
    "file_name": "Light.l69.json",
    "is_locked": false,
    "editor_layer": 8,
    "editor_layer_name": "LampsPF",
    "editor_layer_visibility": true
  },
  {
    "file_name": "Light.l19.json",
    "is_locked": false,
    "editor_layer": 8,
    "editor_layer_name": "LampsPF",
    "editor_layer_visibility": true
  },
  {
    "file_name": "Light.f177.json",
    "is_locked": false,
    "editor_layer": 8,
    "editor_layer_name": "LampsPF",
    "editor_layer_visibility": true
  },
  {
    "file_name": "Light.l01.json",
    "is_locked": false,
    "editor_layer": 8,
    "editor_layer_name": "LampsPF",
    "editor_layer_visibility": true
  },
  {
    "file_name": "Light.l111.json",
    "is_locked": false,
    "editor_layer": 8,
    "editor_layer_name": "LampsPF",
    "editor_layer_visibility": true
  },
  {
    "file_name": "Light.l112.json",
    "is_locked": false,
    "editor_layer": 8,
    "editor_layer_name": "LampsPF",
    "editor_layer_visibility": true
  },
  {
    "file_name": "Light.l88.json",
    "is_locked": false,
    "editor_layer": 8,
    "editor_layer_name": "LampsPF",
    "editor_layer_visibility": true
  },
  {
    "file_name": "Light.l87.json",
    "is_locked": false,
    "editor_layer": 8,
    "editor_layer_name": "LampsPF",
    "editor_layer_visibility": true
  },
  {
    "file_name": "Light.l125.json",
    "is_locked": false,
    "editor_layer": 8,
    "editor_layer_name": "LampsPF",
    "editor_layer_visibility": true
  },
  {
    "file_name": "Light.l55.json",
    "is_locked": false,
    "editor_layer": 8,
    "editor_layer_name": "LampsPF",
    "editor_layer_visibility": true
  },
  {
    "file_name": "Light.l131.json",
    "is_locked": false,
    "editor_layer": 8,
    "editor_layer_name": "LampsPF",
    "editor_layer_visibility": true
  },
  {
    "file_name": "Light.l108.json",
    "is_locked": false,
    "editor_layer": 8,
    "editor_layer_name": "LampsPF",
    "editor_layer_visibility": true
  },
  {
    "file_name": "Light.l126.json",
    "is_locked": false,
    "editor_layer": 8,
    "editor_layer_name": "LampsPF",
    "editor_layer_visibility": true
  },
  {
    "file_name": "Light.l122.json",
    "is_locked": false,
    "editor_layer": 8,
    "editor_layer_name": "LampsPF",
    "editor_layer_visibility": true
  },
  {
    "file_name": "Light.l91.json",
    "is_locked": false,
    "editor_layer": 8,
    "editor_layer_name": "LampsPF",
    "editor_layer_visibility": true
  },
  {
    "file_name": "Light.l78.json",
    "is_locked": false,
    "editor_layer": 8,
    "editor_layer_name": "LampsPF",
    "editor_layer_visibility": true
  },
  {
    "file_name": "Light.l48.json",
    "is_locked": false,
    "editor_layer": 8,
    "editor_layer_name": "LampsPF",
    "editor_layer_visibility": true
  },
  {
    "file_name": "Light.l39.json",
    "is_locked": false,
    "editor_layer": 8,
    "editor_layer_name": "LampsPF",
    "editor_layer_visibility": true
  },
  {
    "file_name": "Light.l62.json",
    "is_locked": false,
    "editor_layer": 8,
    "editor_layer_name": "LampsPF",
    "editor_layer_visibility": true
  },
  {
    "file_name": "Light.l134.json",
    "is_locked": false,
    "editor_layer": 8,
    "editor_layer_name": "LampsPF",
    "editor_layer_visibility": true
  },
  {
    "file_name": "Light.l135.json",
    "is_locked": false,
    "editor_layer": 8,
    "editor_layer_name": "LampsPF",
    "editor_layer_visibility": true
  },
  {
    "file_name": "Light.l16.json",
    "is_locked": false,
    "editor_layer": 8,
    "editor_layer_name": "LampsPF",
    "editor_layer_visibility": true
  },
  {
    "file_name": "Light.l12.json",
    "is_locked": false,
    "editor_layer": 8,
    "editor_layer_name": "LampsPF",
    "editor_layer_visibility": true
  },
  {
    "file_name": "Light.l113.json",
    "is_locked": false,
    "editor_layer": 8,
    "editor_layer_name": "LampsPF",
    "editor_layer_visibility": true
  },
  {
    "file_name": "Light.l82.json",
    "is_locked": false,
    "editor_layer": 8,
    "editor_layer_name": "LampsPF",
    "editor_layer_visibility": true
  },
  {
    "file_name": "Light.l81.json",
    "is_locked": false,
    "editor_layer": 8,
    "editor_layer_name": "LampsPF",
    "editor_layer_visibility": true
  },
  {
    "file_name": "Light.l99.json",
    "is_locked": false,
    "editor_layer": 8,
    "editor_layer_name": "LampsPF",
    "editor_layer_visibility": true
  },
  {
    "file_name": "Light.l96.json",
    "is_locked": false,
    "editor_layer": 8,
    "editor_layer_name": "LampsPF",
    "editor_layer_visibility": true
  },
  {
    "file_name": "Light.l105.json",
    "is_locked": false,
    "editor_layer": 8,
    "editor_layer_name": "LampsPF",
    "editor_layer_visibility": true
  },
  {
    "file_name": "Light.l140.json",
    "is_locked": false,
    "editor_layer": 8,
    "editor_layer_name": "LampsPF",
    "editor_layer_visibility": true
  },
  {
    "file_name": "Light.l141.json",
    "is_locked": false,
    "editor_layer": 8,
    "editor_layer_name": "LampsPF",
    "editor_layer_visibility": true
  },
  {
    "file_name": "Light.l102.json",
    "is_locked": false,
    "editor_layer": 8,
    "editor_layer_name": "LampsPF",
    "editor_layer_visibility": true
  },
  {
    "file_name": "Light.l101.json",
    "is_locked": false,
    "editor_layer": 8,
    "editor_layer_name": "LampsPF",
    "editor_layer_visibility": true
  },
  {
    "file_name": "Light.f163.json",
    "is_locked": false,
    "editor_layer": 8,
    "editor_layer_name": "LampsPF",
    "editor_layer_visibility": true
  },
  {
    "file_name": "Light.f168.json",
    "is_locked": false,
    "editor_layer": 8,
    "editor_layer_name": "LampsPF",
    "editor_layer_visibility": true
  },
  {
    "file_name": "Light.f176.json",
    "is_locked": false,
    "editor_layer": 8,
    "editor_layer_name": "LampsPF",
    "editor_layer_visibility": true
  },
  {
    "file_name": "Light.l119.json",
    "is_locked": false,
    "editor_layer": 8,
    "editor_layer_name": "LampsPF",
    "editor_layer_visibility": true
  },
  {
    "file_name": "Light.l59.json",
    "is_locked": false,
    "editor_layer": 8,
    "editor_layer_name": "LampsPF",
    "editor_layer_visibility": true
  },
  {
    "file_name": "Light.l36.json",
    "is_locked": false,
    "editor_layer": 8,
    "editor_layer_name": "LampsPF",
    "editor_layer_visibility": true
  },
  {
    "file_name": "Light.l25.json",
    "is_locked": false,
    "editor_layer": 8,
    "editor_layer_name": "LampsPF",
    "editor_layer_visibility": true
  },
  {
    "file_name": "Light.l51.json",
    "is_locked": false,
    "editor_layer": 8,
    "editor_layer_name": "LampsPF",
    "editor_layer_visibility": true
  },
  {
    "file_name": "Light.l52.json",
    "is_locked": false,
    "editor_layer": 8,
    "editor_layer_name": "LampsPF",
    "editor_layer_visibility": true
  },
  {
    "file_name": "Light.f178.json",
    "is_locked": false,
    "editor_layer": 8,
    "editor_layer_name": "FlashLamps",
    "editor_layer_visibility": true
  },
  {
    "file_name": "Light.f179.json",
    "is_locked": false,
    "editor_layer": 8,
    "editor_layer_name": "FlashLamps",
    "editor_layer_visibility": true
  },
  {
    "file_name": "Light.f173.json",
    "is_locked": false,
    "editor_layer": 8,
    "editor_layer_name": "FlashLamps",
    "editor_layer_visibility": true
  },
  {
    "file_name": "Light.f184.json",
    "is_locked": false,
    "editor_layer": 8,
    "editor_layer_name": "FlashLamps",
    "editor_layer_visibility": true
  },
  {
    "file_name": "Light.f161.json",
    "is_locked": false,
    "editor_layer": 8,
    "editor_layer_name": "FlashLamps",
    "editor_layer_visibility": true
  },
  {
    "file_name": "Light.f162.json",
    "is_locked": false,
    "editor_layer": 8,
    "editor_layer_name": "FlashLamps",
    "editor_layer_visibility": true
  },
  {
    "file_name": "Light.f160.json",
    "is_locked": false,
    "editor_layer": 8,
    "editor_layer_name": "FlashLamps",
    "editor_layer_visibility": true
  },
  {
    "file_name": "Light.f172.json",
    "is_locked": false,
    "editor_layer": 8,
    "editor_layer_name": "FlashLamps",
    "editor_layer_visibility": true
  },
  {
    "file_name": "Light.f165.json",
    "is_locked": false,
    "editor_layer": 8,
    "editor_layer_name": "FlashLamps",
    "editor_layer_visibility": true
  },
  {
    "file_name": "Light.f182.json",
    "is_locked": false,
    "editor_layer": 8,
    "editor_layer_name": "FlashLamps",
    "editor_layer_visibility": true
  },
  {
    "file_name": "Light.f175.json",
    "is_locked": false,
    "editor_layer": 8,
    "editor_layer_name": "FlashLamps",
    "editor_layer_visibility": true
  },
  {
    "file_name": "Light.f174.json",
    "is_locked": false,
    "editor_layer": 8,
    "editor_layer_name": "FlashLamps",
    "editor_layer_visibility": true
  },
  {
    "file_name": "Light.l118.json",
    "is_locked": false,
    "editor_layer": 8,
    "editor_layer_name": "LampsPF",
    "editor_layer_visibility": true
  },
  {
    "file_name": "Trigger.sw2.json",
    "is_locked": true,
    "editor_layer": 0,
    "editor_layer_name": "switchs",
    "editor_layer_visibility": true
  },
  {
    "file_name": "Light.l22.json",
    "is_locked": false,
    "editor_layer": 8,
    "editor_layer_name": "LampsPF",
    "editor_layer_visibility": true
  },
  {
    "file_name": "Light.f170.json",
    "is_locked": false,
    "editor_layer": 8,
    "editor_layer_name": "FlashLamps",
    "editor_layer_visibility": true
  },
  {
    "file_name": "Primitive.playfield_mesh.json",
    "is_locked": true,
    "editor_layer": 0,
    "editor_layer_name": "playfield",
    "editor_layer_visibility": true
  },
  {
    "file_name": "Ramp.Ramp003.json",
    "is_locked": true,
    "editor_layer": 0,
    "editor_layer_name": "Layer1Ramps",
    "editor_layer_visibility": true
  },
  {
    "file_name": "Ramp.Ramp004.json",
    "is_locked": true,
    "editor_layer": 0,
    "editor_layer_name": "Layer1Ramps",
    "editor_layer_visibility": true
  },
  {
    "file_name": "Ramp.Ramp005.json",
    "is_locked": true,
    "editor_layer": 0,
    "editor_layer_name": "Layer1Ramps",
    "editor_layer_visibility": true
  },
  {
    "file_name": "Ramp.Ramp006.json",
    "is_locked": true,
    "editor_layer": 0,
    "editor_layer_name": "Layer1Ramps",
    "editor_layer_visibility": true
  },
  {
    "file_name": "Wall.wall2.json",
    "is_locked": true,
    "editor_layer": 0,
    "editor_layer_name": "Layer1Walls",
    "editor_layer_visibility": true
  },
  {
    "file_name": "Wall.wall1.json",
    "is_locked": true,
    "editor_layer": 0,
    "editor_layer_name": "Layer1Walls",
    "editor_layer_visibility": true
  },
  {
    "file_name": "Wall.rubber1.json",
    "is_locked": true,
    "editor_layer": 0,
    "editor_layer_name": "Layer1Walls",
    "editor_layer_visibility": true
  },
  {
    "file_name": "Wall.LeftSlingshot.json",
    "is_locked": true,
    "editor_layer": 0,
    "editor_layer_name": "Layer1Walls",
    "editor_layer_visibility": true
  },
  {
    "file_name": "Rubber.LSling.json",
    "is_locked": true,
    "editor_layer": 0,
    "editor_layer_name": "Layer1Walls",
    "editor_layer_visibility": true
  },
  {
    "file_name": "Primitive.zCol_Rubber_Post017.json",
    "is_locked": true,
    "editor_layer": 3,
    "editor_layer_name": "Layer1Physics",
    "editor_layer_visibility": true
  },
  {
    "file_name": "Primitive.zCol_Rubber_Post009.json",
    "is_locked": true,
    "editor_layer": 3,
    "editor_layer_name": "Layer1Physics",
    "editor_layer_visibility": true
  },
  {
    "file_name": "Primitive.zCol_Rubber_Post011.json",
    "is_locked": true,
    "editor_layer": 3,
    "editor_layer_name": "Layer1Physics",
    "editor_layer_visibility": true
  },
  {
    "file_name": "Primitive.EndPoint2LS.json",
    "is_locked": true,
    "editor_layer": 1,
    "editor_layer_name": "Layer1Physics",
    "editor_layer_visibility": true
  },
  {
    "file_name": "Primitive.EndPoint1LS.json",
    "is_locked": true,
    "editor_layer": 1,
    "editor_layer_name": "Layer1Physics",
    "editor_layer_visibility": true
  },
  {
    "file_name": "Wall.rubber2.json",
    "is_locked": true,
    "editor_layer": 0,
    "editor_layer_name": "Layer1Walls",
    "editor_layer_visibility": true
  },
  {
    "file_name": "Wall.RightSlingshot.json",
    "is_locked": true,
    "editor_layer": 0,
    "editor_layer_name": "Layer1Walls",
    "editor_layer_visibility": true
  },
  {
    "file_name": "Rubber.RSling.json",
    "is_locked": true,
    "editor_layer": 0,
    "editor_layer_name": "Layer1Walls",
    "editor_layer_visibility": true
  },
  {
    "file_name": "Primitive.zCol_Rubber_Post008.json",
    "is_locked": true,
    "editor_layer": 3,
    "editor_layer_name": "Layer1Physics",
    "editor_layer_visibility": true
  },
  {
    "file_name": "Primitive.zCol_Rubber_Post010.json",
    "is_locked": true,
    "editor_layer": 3,
    "editor_layer_name": "Layer1Physics",
    "editor_layer_visibility": true
  },
  {
    "file_name": "Primitive.zCol_Rubber_Post012.json",
    "is_locked": true,
    "editor_layer": 3,
    "editor_layer_name": "Layer1Physics",
    "editor_layer_visibility": true
  },
  {
    "file_name": "Primitive.EndPoint2RS.json",
    "is_locked": true,
    "editor_layer": 1,
    "editor_layer_name": "Layer1Physics",
    "editor_layer_visibility": true
  },
  {
    "file_name": "Primitive.EndPoint1RS.json",
    "is_locked": true,
    "editor_layer": 1,
    "editor_layer_name": "Layer1Physics",
    "editor_layer_visibility": true
  },
  {
    "file_name": "Wall.Wall002.json",
    "is_locked": true,
    "editor_layer": 0,
    "editor_layer_name": "Layer1Walls",
    "editor_layer_visibility": true
  },
  {
    "file_name": "Wall.Wall013.json",
    "is_locked": true,
    "editor_layer": 0,
    "editor_layer_name": "Layer1Walls",
    "editor_layer_visibility": true
  },
  {
    "file_name": "LightSequencer.LightSeq.json",
    "is_locked": false,
    "editor_layer": 0,
    "editor_layer_name": "Main Layer",
    "editor_layer_visibility": true
  },
  {
    "file_name": "Primitive.lout_medium.json",
    "is_locked": true,
    "editor_layer": 3,
    "editor_layer_name": "Layer1Physics",
    "editor_layer_visibility": true
  },
  {
    "file_name": "Primitive.zCol_Rubber_Post013.json",
    "is_locked": true,
    "editor_layer": 3,
    "editor_layer_name": "Layer1Physics",
    "editor_layer_visibility": true
  },
  {
    "file_name": "Primitive.lout_extra.json",
    "is_locked": true,
    "editor_layer": 3,
    "editor_layer_name": "Layer1Physics",
    "editor_layer_visibility": true
  },
  {
    "file_name": "Primitive.zCol_Rubber_Post014.json",
    "is_locked": true,
    "editor_layer": 3,
    "editor_layer_name": "Layer1Physics",
    "editor_layer_visibility": true
  },
  {
    "file_name": "Primitive.zCol_Rubber_Post015.json",
    "is_locked": true,
    "editor_layer": 3,
    "editor_layer_name": "Layer1Physics",
    "editor_layer_visibility": true
  },
  {
    "file_name": "Primitive.zCol_Rubber_Post016.json",
    "is_locked": true,
    "editor_layer": 3,
    "editor_layer_name": "Layer1Physics",
    "editor_layer_visibility": true
  },
  {
    "file_name": "Wall.LeftSlingshot001.json",
    "is_locked": true,
    "editor_layer": 0,
    "editor_layer_name": "Layer1Walls",
    "editor_layer_visibility": true
  },
  {
    "file_name": "Bumper.Bumper2.json",
    "is_locked": true,
    "editor_layer": 0,
    "editor_layer_name": "Bumpers",
    "editor_layer_visibility": true
  },
  {
    "file_name": "Bumper.Bumper3.json",
    "is_locked": true,
    "editor_layer": 0,
    "editor_layer_name": "Bumpers",
    "editor_layer_visibility": true
  },
  {
    "file_name": "Wall.Wall9.json",
    "is_locked": true,
    "editor_layer": 6,
    "editor_layer_name": "UpperPF",
    "editor_layer_visibility": true
  },
  {
    "file_name": "Wall.Wall217.json",
    "is_locked": false,
    "editor_layer": 6,
    "editor_layer_name": "UpperPF",
    "editor_layer_visibility": true
  },
  {
    "file_name": "Wall.Wall218.json",
    "is_locked": false,
    "editor_layer": 6,
    "editor_layer_name": "UpperPF",
    "editor_layer_visibility": true
  },
  {
    "file_name": "Flipper.UpRightFlipper.json",
    "is_locked": false,
    "editor_layer": 6,
    "editor_layer_name": "UpperPF",
    "editor_layer_visibility": true
  },
  {
    "file_name": "Rubber.debug_BLR3.json",
    "is_locked": true,
    "editor_layer": 1,
    "editor_layer_name": "ShotTester",
    "editor_layer_visibility": true
  },
  {
    "file_name": "Wall.debug_BLW3.json",
    "is_locked": true,
    "editor_layer": 1,
    "editor_layer_name": "ShotTester",
    "editor_layer_visibility": true
  },
  {
    "file_name": "Rubber.debug_BLR1.json",
    "is_locked": true,
    "editor_layer": 1,
    "editor_layer_name": "ShotTester",
    "editor_layer_visibility": true
  },
  {
    "file_name": "Wall.debug_BLW1.json",
    "is_locked": true,
    "editor_layer": 1,
    "editor_layer_name": "ShotTester",
    "editor_layer_visibility": true
  },
  {
    "file_name": "Rubber.debug_BLR2.json",
    "is_locked": true,
    "editor_layer": 1,
    "editor_layer_name": "ShotTester",
    "editor_layer_visibility": true
  },
  {
    "file_name": "Wall.debug_BLW2.json",
    "is_locked": true,
    "editor_layer": 1,
    "editor_layer_name": "ShotTester",
    "editor_layer_visibility": true
  },
  {
    "file_name": "Primitive.debug_BLP3.json",
    "is_locked": true,
    "editor_layer": 1,
    "editor_layer_name": "ShotTester",
    "editor_layer_visibility": true
  },
  {
    "file_name": "Primitive.debug_BLP1.json",
    "is_locked": true,
    "editor_layer": 1,
    "editor_layer_name": "ShotTester",
    "editor_layer_visibility": true
  },
  {
    "file_name": "Primitive.debug_BLP2.json",
    "is_locked": true,
    "editor_layer": 1,
    "editor_layer_name": "ShotTester",
    "editor_layer_visibility": true
  },
  {
    "file_name": "Kicker.debugKicker.json",
    "is_locked": true,
    "editor_layer": 1,
    "editor_layer_name": "ShotTester",
    "editor_layer_visibility": true
  },
  {
    "file_name": "Primitive.debugKickAim.json",
    "is_locked": true,
    "editor_layer": 1,
    "editor_layer_name": "ShotTester",
    "editor_layer_visibility": true
  },
  {
    "file_name": "Wall.Wall014.json",
    "is_locked": false,
    "editor_layer": 0,
    "editor_layer_name": "UpperPF",
    "editor_layer_visibility": true
  },
  {
    "file_name": "Primitive.Primitive001.json",
    "is_locked": false,
    "editor_layer": 0,
    "editor_layer_name": "UpperPF",
    "editor_layer_visibility": true
  },
  {
    "file_name": "Ramp.Ramp011.json",
    "is_locked": false,
    "editor_layer": 0,
    "editor_layer_name": "UpperPF",
    "editor_layer_visibility": true
  },
  {
    "file_name": "Ramp.Ramp012.json",
    "is_locked": false,
    "editor_layer": 0,
    "editor_layer_name": "UpperPF",
    "editor_layer_visibility": true
  },
  {
    "file_name": "Ramp.Ramp013.json",
    "is_locked": false,
    "editor_layer": 0,
    "editor_layer_name": "UpperPF",
    "editor_layer_visibility": true
  },
  {
    "file_name": "Ramp.Ramp014.json",
    "is_locked": false,
    "editor_layer": 0,
    "editor_layer_name": "Layer1Walls",
    "editor_layer_visibility": true
  },
  {
    "file_name": "Spinner.Spinner001.json",
    "is_locked": false,
    "editor_layer": 0,
    "editor_layer_name": "Layer1Walls",
    "editor_layer_visibility": true
  },
  {
    "file_name": "Bumper.Bumper1.json",
    "is_locked": true,
    "editor_layer": 0,
    "editor_layer_name": "Bumpers",
    "editor_layer_visibility": true
  },
  {
    "file_name": "Primitive.zCol_Rubber_Post018.json",
    "is_locked": true,
    "editor_layer": 3,
    "editor_layer_name": "Layer1Physics",
    "editor_layer_visibility": true
  },
  {
    "file_name": "Wall.RubberBand006.json",
    "is_locked": true,
    "editor_layer": 0,
    "editor_layer_name": "Layer1Walls",
    "editor_layer_visibility": true
  },
  {
    "file_name": "Primitive.zCol_Rubber_Post019.json",
    "is_locked": true,
    "editor_layer": 3,
    "editor_layer_name": "Layer1Physics",
    "editor_layer_visibility": true
  },
  {
    "file_name": "Ramp.Ramp010.json",
    "is_locked": true,
    "editor_layer": 0,
    "editor_layer_name": "Layer1Walls",
    "editor_layer_visibility": true
  },
  {
    "file_name": "Primitive.zCol_Rubber_716_001.json",
    "is_locked": true,
    "editor_layer": 1,
    "editor_layer_name": "Layer1Physics",
    "editor_layer_visibility": true
  },
  {
    "file_name": "Primitive.zCol_Rubber_716_002.json",
    "is_locked": true,
    "editor_layer": 1,
    "editor_layer_name": "Layer1Physics",
    "editor_layer_visibility": true
  },
  {
    "file_name": "Ramp.Ramp015.json",
    "is_locked": true,
    "editor_layer": 0,
    "editor_layer_name": "Layer1Walls",
    "editor_layer_visibility": true
  },
  {
    "file_name": "Ramp.Ramp007.json",
    "is_locked": true,
    "editor_layer": 0,
    "editor_layer_name": "Layer1Walls",
    "editor_layer_visibility": true
  },
  {
    "file_name": "Ramp.Ramp016.json",
    "is_locked": false,
    "editor_layer": 0,
    "editor_layer_name": "Layer1Walls",
    "editor_layer_visibility": true
  },
  {
    "file_name": "Wall.Wall003.json",
    "is_locked": true,
    "editor_layer": 0,
    "editor_layer_name": "Layer1Walls",
    "editor_layer_visibility": true
  },
  {
    "file_name": "Primitive.zCol_Rubber_716_003.json",
    "is_locked": true,
    "editor_layer": 1,
    "editor_layer_name": "Layer1Physics",
    "editor_layer_visibility": true
  },
  {
    "file_name": "Ramp.Ramp008.json",
    "is_locked": true,
    "editor_layer": 0,
    "editor_layer_name": "Layer1Walls",
    "editor_layer_visibility": true
  },
  {
    "file_name": "Ramp.Ramp017.json",
    "is_locked": true,
    "editor_layer": 0,
    "editor_layer_name": "Layer1Ramps",
    "editor_layer_visibility": true
  },
  {
    "file_name": "Ramp.Ramp019.json",
    "is_locked": true,
    "editor_layer": 0,
    "editor_layer_name": "Layer1Ramps",
    "editor_layer_visibility": true
  },
  {
    "file_name": "Ramp.Ramp020.json",
    "is_locked": true,
    "editor_layer": 0,
    "editor_layer_name": "Layer1Ramps",
    "editor_layer_visibility": true
  },
  {
    "file_name": "Ramp.Ramp021.json",
    "is_locked": true,
    "editor_layer": 0,
    "editor_layer_name": "Layer1Ramps",
    "editor_layer_visibility": true
  },
  {
    "file_name": "Spinner.Spinner002.json",
    "is_locked": true,
    "editor_layer": 0,
    "editor_layer_name": "Layer1Walls",
    "editor_layer_visibility": true
  },
  {
    "file_name": "Wall.Wall012.json",
    "is_locked": false,
    "editor_layer": 0,
    "editor_layer_name": "Main Layer",
    "editor_layer_visibility": true
  },
  {
    "file_name": "Ramp.Ramp023.json",
    "is_locked": false,
    "editor_layer": 0,
    "editor_layer_name": "Subway",
    "editor_layer_visibility": true
  },
  {
    "file_name": "Wall.Wall005.json",
    "is_locked": false,
    "editor_layer": 0,
    "editor_layer_name": "Subway",
    "editor_layer_visibility": true
  },
  {
    "file_name": "Wall.Wall008.json",
    "is_locked": false,
    "editor_layer": 0,
    "editor_layer_name": "Subway",
    "editor_layer_visibility": true
  },
  {
    "file_name": "Trigger.sw39001.json",
    "is_locked": false,
    "editor_layer": 0,
    "editor_layer_name": "Subway",
    "editor_layer_visibility": true
  },
  {
    "file_name": "Primitive.zCol_Rubber_Post001.json",
    "is_locked": true,
    "editor_layer": 3,
    "editor_layer_name": "Layer1Physics",
    "editor_layer_visibility": true
  },
  {
    "file_name": "Primitive.lout_extra001.json",
    "is_locked": true,
    "editor_layer": 3,
    "editor_layer_name": "Layer1Physics",
    "editor_layer_visibility": true
  },
  {
    "file_name": "Trigger.sw001.json",
    "is_locked": true,
    "editor_layer": 0,
    "editor_layer_name": "switchs",
    "editor_layer_visibility": true
  },
  {
    "file_name": "Trigger.sw002.json",
    "is_locked": true,
    "editor_layer": 0,
    "editor_layer_name": "switchs",
    "editor_layer_visibility": true
  },
  {
    "file_name": "Primitive.Primitive004.json",
    "is_locked": true,
    "editor_layer": 0,
    "editor_layer_name": "Layer1Walls",
    "editor_layer_visibility": true
  },
  {
    "file_name": "Primitive.Primitive005.json",
    "is_locked": true,
    "editor_layer": 0,
    "editor_layer_name": "UpperPF",
    "editor_layer_visibility": true
  },
  {
    "file_name": "Wall.Wall007.json",
    "is_locked": false,
    "editor_layer": 0,
    "editor_layer_name": "UpperPF",
    "editor_layer_visibility": true
  },
  {
    "file_name": "Wall.Wall009.json",
    "is_locked": false,
    "editor_layer": 0,
    "editor_layer_name": "New Layer 0",
    "editor_layer_visibility": true
  },
  {
    "file_name": "Wall.Wall010.json",
    "is_locked": false,
    "editor_layer": 0,
    "editor_layer_name": "Layer1Walls",
    "editor_layer_visibility": true
  },
  {
    "file_name": "Wall.waterfalldiverter.json",
    "is_locked": true,
    "editor_layer": 0,
    "editor_layer_name": "Layer1Walls",
    "editor_layer_visibility": true
  },
  {
    "file_name": "Wall.Wall017.json",
    "is_locked": false,
    "editor_layer": 0,
    "editor_layer_name": "New Layer 0",
    "editor_layer_visibility": true
  },
  {
    "file_name": "Wall.Wall020.json",
    "is_locked": false,
    "editor_layer": 0,
    "editor_layer_name": "New Layer 0",
    "editor_layer_visibility": true
  },
  {
    "file_name": "Wall.Wall021.json",
    "is_locked": false,
    "editor_layer": 0,
    "editor_layer_name": "New Layer 0",
    "editor_layer_visibility": true
  },
  {
    "file_name": "Primitive.Primitive007.json",
    "is_locked": false,
    "editor_layer": 0,
    "editor_layer_name": "New Layer 0",
    "editor_layer_visibility": true
  },
  {
    "file_name": "Kicker.Kicker001.json",
    "is_locked": false,
    "editor_layer": 0,
    "editor_layer_name": "New Layer 0",
    "editor_layer_visibility": true
  },
  {
    "file_name": "Ramp.Ramp009.json",
    "is_locked": false,
    "editor_layer": 0,
    "editor_layer_name": "playfield",
    "editor_layer_visibility": true
  },
  {
    "file_name": "Wall.Wall016.json",
    "is_locked": false,
    "editor_layer": 0,
    "editor_layer_name": "playfield",
    "editor_layer_visibility": true
  },
  {
    "file_name": "Ramp.Ramp024.json",
    "is_locked": false,
    "editor_layer": 0,
    "editor_layer_name": "Layer1Walls",
    "editor_layer_visibility": true
  },
  {
    "file_name": "Primitive.Primitive006.json",
    "is_locked": false,
    "editor_layer": 0,
    "editor_layer_name": "playfield",
    "editor_layer_visibility": true
  },
  {
    "file_name": "Primitive.lout_medium001.json",
    "is_locked": true,
    "editor_layer": 3,
    "editor_layer_name": "Layer1Physics",
    "editor_layer_visibility": true
  },
  {
    "file_name": "Primitive.lout_medium002.json",
    "is_locked": true,
    "editor_layer": 3,
    "editor_layer_name": "Layer1Physics",
    "editor_layer_visibility": true
  },
  {
    "file_name": "Wall.RubberBand001.json",
    "is_locked": true,
    "editor_layer": 0,
    "editor_layer_name": "Layer1Walls",
    "editor_layer_visibility": true
  },
  {
    "file_name": "Spinner.Spinner003.json",
    "is_locked": false,
    "editor_layer": 0,
    "editor_layer_name": "Layer1Walls",
    "editor_layer_visibility": true
  },
  {
    "file_name": "Ramp.Ramp018.json",
    "is_locked": false,
    "editor_layer": 0,
    "editor_layer_name": "Layer1Ramps",
    "editor_layer_visibility": true
  },
  {
    "file_name": "Ramp.Ramp022.json",
    "is_locked": false,
    "editor_layer": 0,
    "editor_layer_name": "Layer1Ramps",
    "editor_layer_visibility": true
  },
  {
    "file_name": "Ramp.Ramp025.json",
    "is_locked": false,
    "editor_layer": 0,
    "editor_layer_name": "Layer1Ramps",
    "editor_layer_visibility": true
  },
  {
    "file_name": "Wall.Wall019.json",
    "is_locked": false,
    "editor_layer": 6,
    "editor_layer_name": "UpperPF",
    "editor_layer_visibility": true
  },
  {
    "file_name": "Primitive.lout_medium003.json",
    "is_locked": false,
    "editor_layer": 3,
    "editor_layer_name": "UpperPF",
    "editor_layer_visibility": true
  },
  {
    "file_name": "Wall.sw04.json",
    "is_locked": false,
    "editor_layer": 4,
    "editor_layer_name": "DropTargets",
    "editor_layer_visibility": true
  },
  {
    "file_name": "Wall.sw04a.json",
    "is_locked": false,
    "editor_layer": 4,
    "editor_layer_name": "DropTargets",
    "editor_layer_visibility": true
  },
  {
    "file_name": "Primitive.scoopeject.json",
    "is_locked": true,
    "editor_layer": 0,
    "editor_layer_name": "Main Layer",
    "editor_layer_visibility": true
  },
  {
    "file_name": "Wall.sw01a.json",
    "is_locked": true,
    "editor_layer": 4,
    "editor_layer_name": "DropTargets",
    "editor_layer_visibility": true
  },
  {
    "file_name": "Light.l01a.json",
    "is_locked": false,
    "editor_layer": 8,
    "editor_layer_name": "VLM.Lightmaps",
    "editor_layer_visibility": true
  },
  {
    "file_name": "Wall.sw05.json",
    "is_locked": false,
    "editor_layer": 4,
    "editor_layer_name": "DropTargets",
    "editor_layer_visibility": true
  },
  {
    "file_name": "Wall.sw05a.json",
    "is_locked": false,
    "editor_layer": 4,
    "editor_layer_name": "DropTargets",
    "editor_layer_visibility": true
  },
  {
    "file_name": "Wall.sw06a.json",
    "is_locked": false,
    "editor_layer": 4,
    "editor_layer_name": "DropTargets",
    "editor_layer_visibility": true
  },
  {
    "file_name": "Wall.sw06.json",
    "is_locked": false,
    "editor_layer": 4,
    "editor_layer_name": "DropTargets",
    "editor_layer_visibility": true
  },
  {
    "file_name": "Wall.sw08.json",
    "is_locked": false,
    "editor_layer": 4,
    "editor_layer_name": "DropTargets",
    "editor_layer_visibility": true
  },
  {
    "file_name": "Wall.sw08a.json",
    "is_locked": false,
    "editor_layer": 4,
    "editor_layer_name": "DropTargets",
    "editor_layer_visibility": true
  },
  {
    "file_name": "Wall.sw09.json",
    "is_locked": false,
    "editor_layer": 4,
    "editor_layer_name": "DropTargets",
    "editor_layer_visibility": true
  },
  {
    "file_name": "Wall.sw09a.json",
    "is_locked": false,
    "editor_layer": 4,
    "editor_layer_name": "DropTargets",
    "editor_layer_visibility": true
  },
  {
    "file_name": "Wall.sw10.json",
    "is_locked": false,
    "editor_layer": 4,
    "editor_layer_name": "DropTargets",
    "editor_layer_visibility": true
  },
  {
    "file_name": "Wall.sw10a.json",
    "is_locked": false,
    "editor_layer": 4,
    "editor_layer_name": "DropTargets",
    "editor_layer_visibility": true
  },
  {
    "file_name": "Trigger.sw99.json",
    "is_locked": false,
    "editor_layer": 0,
    "editor_layer_name": "VLM.Visuals",
    "editor_layer_visibility": true
  },
  {
    "file_name": "Primitive.BM_Cab.json",
    "is_locked": true,
    "editor_layer": 0,
    "editor_layer_name": "VLM.Visuals",
    "editor_layer_visibility": true
  },
  {
    "file_name": "Primitive.BM_PF.json",
    "is_locked": true,
    "editor_layer": 0,
    "editor_layer_name": "VLM.Visuals",
    "editor_layer_visibility": true
  },
  {
    "file_name": "Primitive.BM_Panther.json",
    "is_locked": true,
    "editor_layer": 0,
    "editor_layer_name": "VLM.Visuals",
    "editor_layer_visibility": true
  },
  {
    "file_name": "Primitive.BM_Parts.json",
    "is_locked": true,
    "editor_layer": 0,
    "editor_layer_name": "VLM.Visuals",
    "editor_layer_visibility": true
  },
  {
    "file_name": "Primitive.BM_sw04.json",
    "is_locked": true,
    "editor_layer": 0,
    "editor_layer_name": "VLM.Visuals",
    "editor_layer_visibility": true
  },
  {
    "file_name": "Primitive.BM_sw05.json",
    "is_locked": true,
    "editor_layer": 0,
    "editor_layer_name": "VLM.Visuals",
    "editor_layer_visibility": true
  },
  {
    "file_name": "Primitive.BM_sw06.json",
    "is_locked": true,
    "editor_layer": 0,
    "editor_layer_name": "VLM.Visuals",
    "editor_layer_visibility": true
  },
  {
    "file_name": "Primitive.BM_sw08.json",
    "is_locked": true,
    "editor_layer": 0,
    "editor_layer_name": "VLM.Visuals",
    "editor_layer_visibility": true
  },
  {
    "file_name": "Primitive.BM_sw09.json",
    "is_locked": true,
    "editor_layer": 0,
    "editor_layer_name": "VLM.Visuals",
    "editor_layer_visibility": true
  },
  {
    "file_name": "Primitive.BM_sw10.json",
    "is_locked": true,
    "editor_layer": 0,
    "editor_layer_name": "VLM.Visuals",
    "editor_layer_visibility": true
  },
  {
    "file_name": "Primitive.BM_sw11.json",
    "is_locked": true,
    "editor_layer": 0,
    "editor_layer_name": "VLM.Visuals",
    "editor_layer_visibility": true
  },
  {
    "file_name": "Primitive.BM_sw12.json",
    "is_locked": true,
    "editor_layer": 0,
    "editor_layer_name": "VLM.Visuals",
    "editor_layer_visibility": true
  },
  {
    "file_name": "Primitive.BM_sw13.json",
    "is_locked": true,
    "editor_layer": 0,
    "editor_layer_name": "VLM.Visuals",
    "editor_layer_visibility": true
  },
  {
    "file_name": "Primitive.BM_sw15.json",
    "is_locked": true,
    "editor_layer": 0,
    "editor_layer_name": "VLM.Visuals",
    "editor_layer_visibility": true
  },
  {
    "file_name": "Primitive.BM_sw16.json",
    "is_locked": true,
    "editor_layer": 0,
    "editor_layer_name": "VLM.Visuals",
    "editor_layer_visibility": true
  },
  {
    "file_name": "Primitive.BM_sw17.json",
    "is_locked": true,
    "editor_layer": 0,
    "editor_layer_name": "VLM.Visuals",
    "editor_layer_visibility": true
  },
  {
    "file_name": "Primitive.BM_targetbank.json",
    "is_locked": true,
    "editor_layer": 0,
    "editor_layer_name": "VLM.Visuals",
    "editor_layer_visibility": true
  },
  {
    "file_name": "HitTarget.sw13.json",
    "is_locked": false,
    "editor_layer": 1,
    "editor_layer_name": "StandUpTargets",
    "editor_layer_visibility": true
  },
  {
    "file_name": "HitTarget.sw12.json",
    "is_locked": false,
    "editor_layer": 1,
    "editor_layer_name": "StandUpTargets",
    "editor_layer_visibility": true
  },
  {
    "file_name": "HitTarget.sw11.json",
    "is_locked": false,
    "editor_layer": 1,
    "editor_layer_name": "StandUpTargets",
    "editor_layer_visibility": true
  },
  {
    "file_name": "HitTarget.sw15.json",
    "is_locked": false,
    "editor_layer": 1,
    "editor_layer_name": "StandUpTargets",
    "editor_layer_visibility": true
  },
  {
    "file_name": "HitTarget.sw16.json",
    "is_locked": false,
    "editor_layer": 1,
    "editor_layer_name": "StandUpTargets",
    "editor_layer_visibility": true
  },
  {
    "file_name": "HitTarget.sw17.json",
    "is_locked": false,
    "editor_layer": 1,
    "editor_layer_name": "StandUpTargets",
    "editor_layer_visibility": true
  },
  {
    "file_name": "Wall.Wall018.json",
    "is_locked": false,
    "editor_layer": 0,
    "editor_layer_name": "StandUpTargets",
    "editor_layer_visibility": true
  }
]