{
  "Flipper": {
    "center": {
      "x": 273.34012,
      "y": 1851.0549
    },
    "base_radius": 20.75,
    "end_radius": 11.5,
    "flipper_radius_max": 114.0,
    "return_": 0.066,
    "start_angle": 121.0,
    "end_angle": 69.0,
    "override_physics": 0,
    "mass": 1.0,
    "is_timer_enabled": false,
    "timer_interval": 100,
    "surface": "",
    "material": "",
    "name": "LeftFlipper",
    "rubber_material": "Rubber Yellow",
    "rubber_thickness_int": 5,
    "rubber_thickness": 5.8825,
    "rubber_height_int": 17,
    "rubber_height": 17.6475,
    "rubber_width_int": 23,
    "rubber_width": 23.53,
    "strength": 3200.0,
    "elasticity": 0.86,
    "elasticity_falloff": 0.12,
    "friction": 0.9,
    "ramp_up": 2.5,
    "scatter": 0.0,
    "torque_damping": 0.1041667,
    "torque_damping_angle": 6.0,
    "flipper_radius_min": 0.0,
    "is_visible": true,
    "is_enabled": true,
    "height": 50.0,
    "image": "",
    "is_reflection_enabled": false
  }
}