{
  "Trigger": {
    "center": {
      "x": 894.0369,
      "y": 810.1261
    },
    "radius": 25.0,
    "rotation": 0.0,
    "wire_thickness": 0.0,
    "scale_x": 1.0,
    "scale_y": 1.0,
    "is_timer_enabled": false,
    "timer_interval": 100,
    "material": "",
    "surface": "",
    "is_visible": true,
    "is_enabled": true,
    "hit_height": 50.0,
    "name": "BIPL_Top",
    "shape": 0,
    "anim_speed": 1.0,
    "is_reflection_enabled": false,
    "drag_points": [
      {
        "x": 864.0369,
        "y": 780.1261,
        "z": 0.0,
        "smooth": false,
        "is_slingshot": false,
        "has_auto_texture": true,
        "tex_coord": 0.0,
        "is_locked": false,
        "editor_layer": 0,
        "editor_layer_name": "",
        "editor_layer_visibility": true
      },
      {
        "x": 866.97797,
        "y": 782.05194,
        "z": 0.0,
        "smooth": false,
        "is_slingshot": false,
        "has_auto_texture": true,
        "tex_coord": 0.0,
        "is_locked": false,
        "editor_layer": 0,
        "editor_layer_name": "",
        "editor_layer_visibility": true
      },
      {
        "x": 922.58826,
        "y": 521.66235,
        "z": 0.0,
        "smooth": false,
        "is_slingshot": false,
        "has_auto_texture": true,
        "tex_coord": 0.0,
        "is_locked": false,
        "editor_layer": 0,
        "editor_layer_name": "",
        "editor_layer_visibility": true
      },
      {
        "x": 922.10535,
        "y": 509.9917,
        "z": 0.0,
        "smooth": false,
        "is_slingshot": false,
        "has_auto_texture": true,
        "tex_coord": 0.0,
        "is_locked": false,
        "editor_layer": 0,
        "editor_layer_name": "",
        "editor_layer_visibility": true
      },
      {
        "x": 885.3947,
        "y": 685.3569,
        "z": 0.0,
        "smooth": false,
        "is_slingshot": false,
        "has_auto_texture": true,
        "tex_coord": 0.0,
        "is_locked": false,
        "editor_layer": 0,
        "editor_layer_name": "",
        "editor_layer_visibility": true
      }
    ]
  }
}