{
  "Trigger": {
    "center": {
      "x": 122.62653,
      "y": 1586.1063
    },
    "radius": 25.0,
    "rotation": 0.0,
    "wire_thickness": 0.0,
    "scale_x": 1.0,
    "scale_y": 1.0,
    "is_timer_enabled": false,
    "timer_interval": 100,
    "material": "Rubber Yellow",
    "surface": "",
    "is_visible": true,
    "is_enabled": true,
    "hit_height": 50.0,
    "name": "sw2",
    "shape": 6,
    "anim_speed": 1.0,
    "is_reflection_enabled": true,
    "drag_points": [
      {
        "x": 103.52541,
        "y": 1565.2816,
        "z": 0.0,
        "smooth": false,
        "is_slingshot": false,
        "has_auto_texture": true,
        "tex_coord": 0.0,
        "is_locked": false,
        "editor_layer": 0,
        "editor_layer_name": "",
        "editor_layer_visibility": true
      },
      {
        "x": 103.52541,
        "y": 1603.3036,
        "z": 0.0,
        "smooth": false,
        "is_slingshot": false,
        "has_auto_texture": true,
        "tex_coord": 0.0,
        "is_locked": false,
        "editor_layer": 0,
        "editor_layer_name": "",
        "editor_layer_visibility": true
      },
      {
        "x": 147.71913,
        "y": 1603.3036,
        "z": 0.0,
        "smooth": false,
        "is_slingshot": false,
        "has_auto_texture": true,
        "tex_coord": 0.0,
        "is_locked": false,
        "editor_layer": 0,
        "editor_layer_name": "",
        "editor_layer_visibility": true
      },
      {
        "x": 147.71916,
        "y": 1565.2816,
        "z": 0.0,
        "smooth": false,
        "is_slingshot": false,
        "has_auto_texture": true,
        "tex_coord": 0.0,
        "is_locked": false,
        "editor_layer": 0,
        "editor_layer_name": "",
        "editor_layer_visibility": true
      }
    ]
  }
}