{
  "Wall": {
    "hit_event": true,
    "is_droppable": false,
    "is_flipbook": false,
    "is_bottom_solid": false,
    "is_collidable": true,
    "is_timer_enabled": false,
    "timer_interval": 100,
    "threshold": 1.0,
    "image": "",
    "side_image": "",
    "side_material": "",
    "top_material": "",
    "slingshot_material": "",
    "height_bottom": 0.0,
    "height_top": 50.0,
    "name": "sw01",
    "display_texture": false,
    "slingshot_force": 80.0,
    "slingshot_threshold": 2.0,
    "elasticity": 0.3,
    "elasticity_falloff": 0.0,
    "friction": 0.3,
    "scatter": 0.0,
    "is_top_bottom_visible": false,
    "slingshot_animation": false,
    "is_side_visible": false,
    "disable_lighting_top_old": null,
    "disable_lighting_top": 0.0,
    "disable_lighting_below": 0.0,
    "is_reflection_enabled": false,
    "physics_material": "zCol_DropTarget",
    "overwrite_physics": false,
    "drag_points": [
      {
        "x": 627.33624,
        "y": 1121.7555,
        "z": 0.0,
        "smooth": false,
        "is_slingshot": false,
        "has_auto_texture": true,
        "tex_coord": 0.0,
        "is_locked": false,
        "editor_layer": 0,
        "editor_layer_name": "",
        "editor_layer_visibility": true
      },
      {
        "x": 611.40875,
        "y": 1149.997,
        "z": 0.0,
        "smooth": false,
        "is_slingshot": false,
        "has_auto_texture": true,
        "tex_coord": 0.0,
        "is_locked": false,
        "editor_layer": 0,
        "editor_layer_name": "",
        "editor_layer_visibility": true
      },
      {
        "x": 612.7459,
        "y": 1191.6653,
        "z": 0.0,
        "smooth": false,
        "is_slingshot": false,
        "has_auto_texture": true,
        "tex_coord": 0.0,
        "is_locked": false,
        "editor_layer": 0,
        "editor_layer_name": "",
        "editor_layer_visibility": true
      },
      {
        "x": 617.5639,
        "y": 1209.5946,
        "z": 0.0,
        "smooth": false,
        "is_slingshot": false,
        "has_auto_texture": true,
        "tex_coord": 0.0,
        "is_locked": false,
        "editor_layer": 0,
        "editor_layer_name": "",
        "editor_layer_visibility": true
      },
      {
        "x": 624.71387,
        "y": 1213.8289,
        "z": 0.0,
        "smooth": true,
        "is_slingshot": false,
        "has_auto_texture": true,
        "tex_coord": 0.0,
        "is_locked": false,
        "editor_layer": 0,
        "editor_layer_name": "",
        "editor_layer_visibility": true
      },
      {
        "x": 637.65436,
        "y": 1213.0693,
        "z": 0.0,
        "smooth": true,
        "is_slingshot": false,
        "has_auto_texture": true,
        "tex_coord": 0.0,
        "is_locked": false,
        "editor_layer": 0,
        "editor_layer_name": "",
        "editor_layer_visibility": true
      },
      {
        "x": 647.8837,
        "y": 1199.0621,
        "z": 0.0,
        "smooth": false,
        "is_slingshot": false,
        "has_auto_texture": true,
        "tex_coord": 0.0,
        "is_locked": false,
        "editor_layer": 0,
        "editor_layer_name": "",
        "editor_layer_visibility": true
      },
      {
        "x": 673.23785,
        "y": 1164.1733,
        "z": 0.0,
        "smooth": false,
        "is_slingshot": false,
        "has_auto_texture": true,
        "tex_coord": 0.0,
        "is_locked": false,
        "editor_layer": 0,
        "editor_layer_name": "",
        "editor_layer_visibility": true
      },
      {
        "x": 674.5687,
        "y": 1139.6145,
        "z": 0.0,
        "smooth": false,
        "is_slingshot": false,
        "has_auto_texture": true,
        "tex_coord": 0.0,
        "is_locked": false,
        "editor_layer": 0,
        "editor_layer_name": "",
        "editor_layer_visibility": true
      },
      {
        "x": 650.3761,
        "y": 1129.3145,
        "z": 0.0,
        "smooth": false,
        "is_slingshot": false,
        "has_auto_texture": true,
        "tex_coord": 0.0,
        "is_locked": false,
        "editor_layer": 0,
        "editor_layer_name": "",
        "editor_layer_visibility": true
      }
    ]
  }
}